compatibleversion/__init__.py
compatibleversion-0.2.17.dist-info/LICENSE
compatibleversion-0.2.17.dist-info/METADATA
compatibleversion-0.2.17.dist-info/WHEEL
compatibleversion-0.2.17.dist-info/entry_points.txt
compatibleversion-0.2.17.dist-info/top_level.txt
compatibleversion-0.2.17.dist-info/RECORD
